muwanx/__init__.py
muwanx/_build_client.py
muwanx/_cli.py
muwanx/app.py
muwanx/builder.py
muwanx/policy.py
muwanx/project.py
muwanx/py.typed
muwanx/scene.py
muwanx/utils.py
muwanx/template/.browserslistrc
muwanx/template/.gitignore
muwanx/template/LICENSE
muwanx/template/README.md
muwanx/template/eslint.config.cjs
muwanx/template/index.html
muwanx/template/package-lock.json
muwanx/template/package.json
muwanx/template/tsconfig.json
muwanx/template/vite.config.ts
muwanx/template/dist/index.html
muwanx/template/dist/logo.svg
muwanx/template/dist/manifest.json
muwanx/template/dist/robots.txt
muwanx/template/dist/assets/Inter-VariableFont_slnt_wght-Cl4AQHp9.ttf
muwanx/template/dist/assets/index-B6uiHnhS.css
muwanx/template/dist/assets/index-D2Jr6wSo.js
muwanx/template/dist/assets/index-D2Jr6wSo.js.map
muwanx/template/dist/assets/mujoco-D3MKgrvB.js
muwanx/template/dist/assets/mujoco-D3MKgrvB.js.map
muwanx/template/public/logo.svg
muwanx/template/public/manifest.json
muwanx/template/public/robots.txt
muwanx/template/src/App.css.ts
muwanx/template/src/App.tsx
muwanx/template/src/AppTheme.ts
muwanx/template/src/index.css
muwanx/template/src/index.tsx
muwanx/template/src/vite-env.d.ts
muwanx/template/src/ControlPanel/ControlPanel.tsx
muwanx/template/src/ControlPanel/FloatingPanel.tsx
muwanx/template/src/ControlPanel/LabeledInput.tsx
muwanx/template/src/ControlPanel/index.ts
"muwanx/template/src/assets/Inter-VariableFont_slnt,wght.ttf"
muwanx/template/src/components/Loader.css
muwanx/template/src/components/Loader.tsx
muwanx/template/src/components/MuwanxViewer.tsx
muwanx/template/src/contexts/LoadingContext.tsx
muwanx/template/src/core/cache/memoryMonitor.ts
muwanx/template/src/core/cache/onnxCacheAdapter.ts
muwanx/template/src/core/cache/resourceTracker.ts
muwanx/template/src/core/cache/sceneCacheManager.ts
muwanx/template/src/core/engine/runtime.ts
muwanx/template/src/core/scene/coordinate.ts
muwanx/template/src/core/scene/lights.ts
muwanx/template/src/core/scene/scene.ts
muwanx-0.0.6.dist-info/METADATA
muwanx-0.0.6.dist-info/WHEEL
muwanx-0.0.6.dist-info/entry_points.txt
muwanx-0.0.6.dist-info/licenses/LICENSE
muwanx-0.0.6.dist-info/RECORD
