Metadata-Version: 2.4
Name: muwanx
Version: 0.0.6
Summary: Browser-based MuJoCo simulation with real-time policy control
Project-URL: GitHub, https://github.com/ttktjmt/muwanx
Author: Muwanx Developers
License: Apache-2.0
License-File: LICENSE
Classifier: Development Status :: 3 - Alpha
Classifier: Intended Audience :: Developers
Classifier: Intended Audience :: Science/Research
Classifier: License :: OSI Approved :: Apache Software License
Classifier: Natural Language :: English
Classifier: Programming Language :: Python :: 3
Classifier: Programming Language :: Python :: 3 :: Only
Classifier: Programming Language :: Python :: 3.9
Classifier: Programming Language :: Python :: 3.10
Classifier: Programming Language :: Python :: 3.11
Classifier: Programming Language :: Python :: 3.12
Classifier: Topic :: Scientific/Engineering
Classifier: Typing :: Typed
Requires-Python: >=3.10
Requires-Dist: mujoco>=3.4.0
Requires-Dist: nodeenv>=1.9.1
Requires-Dist: onnx>=1.20.0
Requires-Dist: wandb>=0.23.1
Provides-Extra: dev
Requires-Dist: nodeenv>=1.9.0; extra == 'dev'
Requires-Dist: pre-commit>=3.3.2; extra == 'dev'
Requires-Dist: pyright>=1.1.407; extra == 'dev'
Requires-Dist: pytest>=9.0.2; extra == 'dev'
Requires-Dist: ruff>=0.14.9; extra == 'dev'
Provides-Extra: examples
Requires-Dist: torch>=2.9.1; extra == 'examples'
